cudagrad/__init__.py
cudagrad/nn.py
cudagrad/tensor.pyi
cudagrad/tensor.so
cudagrad-0.2.8.dist-info/LICENSE
cudagrad-0.2.8.dist-info/METADATA
cudagrad-0.2.8.dist-info/WHEEL
cudagrad-0.2.8.dist-info/top_level.txt
cudagrad-0.2.8.dist-info/RECORD
