Metadata-Version: 2.1
Name: cudagrad
Version: 0.2.8
Summary: A tensor-valued autograd engine for Python
Home-page: https://github.com/yrmo/cudagrad
Author: Ryan Moore
Author-email: Ryan Moore <ryanm.inbox@gmail.com>
License: MIT License
Project-URL: Homepage, https://github.com/yrmo/cudagrad
Project-URL: Bug Tracker, https://github.com/yrmo/cudagrad/issues
Classifier: Programming Language :: Python :: 3
Classifier: Operating System :: OS Independent
Requires-Python: >=3.7
License-File: LICENSE
